dictionary/__init__.py
dictionary/dictionary.py
flyingshark_s_dictionary-2.0.0.dist-info/METADATA
flyingshark_s_dictionary-2.0.0.dist-info/WHEEL
flyingshark_s_dictionary-2.0.0.dist-info/top_level.txt
flyingshark_s_dictionary-2.0.0.dist-info/RECORD
